odoo/addons/delivery_state_manual/README.rst
odoo/addons/delivery_state_manual/__init__.py
odoo/addons/delivery_state_manual/__manifest__.py
odoo/addons/delivery_state_manual/i18n/delivery_state_manual.pot
odoo/addons/delivery_state_manual/i18n/it.po
odoo/addons/delivery_state_manual/models/__init__.py
odoo/addons/delivery_state_manual/models/delivery_carrier.py
odoo/addons/delivery_state_manual/models/stock_picking.py
odoo/addons/delivery_state_manual/readme/CONFIGURE.md
odoo/addons/delivery_state_manual/readme/CONTRIBUTORS.md
odoo/addons/delivery_state_manual/readme/DESCRIPTION.md
odoo/addons/delivery_state_manual/readme/USAGE.md
odoo/addons/delivery_state_manual/static/description/icon.png
odoo/addons/delivery_state_manual/static/description/icon.svg
odoo/addons/delivery_state_manual/static/description/index.html
odoo/addons/delivery_state_manual/tests/__init__.py
odoo/addons/delivery_state_manual/tests/test_delivery_state_manual.py
odoo/addons/delivery_state_manual/views/delivery_carrier_views.xml
odoo/addons/delivery_state_manual/views/stock_picking_views.xml
odoo_addon_delivery_state_manual-16.0.1.0.0.4.dist-info/METADATA
odoo_addon_delivery_state_manual-16.0.1.0.0.4.dist-info/WHEEL
odoo_addon_delivery_state_manual-16.0.1.0.0.4.dist-info/top_level.txt
odoo_addon_delivery_state_manual-16.0.1.0.0.4.dist-info/RECORD
