Metadata-Version: 2.1
Name: odoo-addon-delivery_state_manual
Version: 16.0.1.0.0.4
Summary: Manually edit the delivery state of pickings
Home-page: https://github.com/OCA/delivery-carrier
Author: Sygel, Odoo Community Association (OCA)
Author-email: support@odoo-community.org
License: AGPL-3
Classifier: Programming Language :: Python
Classifier: Framework :: Odoo
Classifier: Framework :: Odoo :: 16.0
Classifier: License :: OSI Approved :: GNU Affero General Public License v3
Requires-Python: >=3.10
Requires-Dist: odoo-addon-delivery-state<16.1dev,>=16.0dev
Requires-Dist: odoo<16.1dev,>=16.0a
